roshareservice/__init__.py
roshareservice/cli.py
roshareservice/roshareservice_config.yaml
roshareservice/service/__init__.py
roshareservice/service/cons.py
roshareservice/service/dbconnection.py
roshareservice/service/main_router.py
roshareservice/service/tushare_router.py
roshareservice/service/user_router.py
roshareservice/tool/__init__.py
roshareservice/tool/cons.py
roshareservice/tool/info_tool.py
roshareservice/tool/request_tool.py
roshareservice/tool/token_tool.py
roshareservice/tool/trafic_tool.py
shihua_roshareservice-0.1.1.dist-info/METADATA
shihua_roshareservice-0.1.1.dist-info/WHEEL
shihua_roshareservice-0.1.1.dist-info/entry_points.txt
shihua_roshareservice-0.1.1.dist-info/top_level.txt
shihua_roshareservice-0.1.1.dist-info/RECORD
