Metadata-Version: 2.1
Name: shihua-roshareservice
Version: 0.1.1
Summary: roshareservice is a python sdk with chinese stock data service.
Home-page: https://github.com/redblue0216/RoShareService
Author: shihua
Author-email: 15021408795@163.com
License: MIT
Requires-Python: >=3.9.13
